fits_to_stamps/__init__.py
fits_to_stamps/fits_to_stamps.py
fits_to_stamps-0.0.4.dist-info/LICENSE.txt
fits_to_stamps-0.0.4.dist-info/METADATA
fits_to_stamps-0.0.4.dist-info/RECORD
fits_to_stamps-0.0.4.dist-info/WHEEL
fits_to_stamps-0.0.4.dist-info/entry_points.txt
fits_to_stamps-0.0.4.dist-info/top_level.txt
