Metadata-Version: 2.1
Name: fits-to-stamps
Version: 0.0.4
Summary: A simple script to convert FITS images to 3 x 3 stamps.
Home-page: https://github.com/waqasbhatti/fits-to-stamps
Author: Waqas Bhatti
Author-email: waqas.afzal.bhatti@gmail.com
License: MIT
Keywords: astronomy
Platform: UNKNOWN
Classifier: Development Status :: 3 - Alpha
Classifier: License :: OSI Approved :: MIT License
Classifier: Intended Audience :: Science/Research
Classifier: Topic :: Scientific/Engineering :: Astronomy
Classifier: Operating System :: OS Independent
Classifier: Programming Language :: Python
Requires-Dist: numpy
Requires-Dist: astropy (>=2.0)
Requires-Dist: Pillow
